clickflare/__init__.py
clickflare/cfclient.py
clickflare/cli.py
clickflare/config.py
clickflare/exceptions.py
clickflare/helpers.py
clickflare/lazy_group.py
clickflare/clis/__init__.py
clickflare/clis/accounts.py
clickflare/clis/accounts_logs.py
clickflare/clis/accounts_logs_audit.py
clickflare/clis/accounts_members.py
clickflare/clis/accounts_roles.py
clickflare/clis/accounts_subscriptions.py
clickflare/clis/accounts_tokens.py
clickflare/clis/ips.py
clickflare/clis/zones.py
clickflare/clis/zones_dns_records.py
clickflare/opinionated_formats/__init__.py
clickflare/opinionated_formats/endpoint_formats.py
clickflare/opinionated_formats/endpoints.py
clickflare-0.0.5.dist-info/METADATA
clickflare-0.0.5.dist-info/WHEEL
clickflare-0.0.5.dist-info/entry_points.txt
clickflare-0.0.5.dist-info/licenses/LICENSE
clickflare-0.0.5.dist-info/RECORD
